licenser_h-1.2.dist-info/licenses/LICENSE
src/__init__.py
src/add_license.py
src/choose_license.py
src/detect_license.py
src/full_licenses.py
src/get_license.py
src/main.py
licenser_h-1.2.dist-info/METADATA
licenser_h-1.2.dist-info/WHEEL
licenser_h-1.2.dist-info/entry_points.txt
licenser_h-1.2.dist-info/top_level.txt
licenser_h-1.2.dist-info/RECORD
