Metadata-Version: 2.4
Name: licenser-h
Version: 1.2
Summary: A simple tool for adding licenses and license headers to your projects.
Author-email: Alex Frutkin <frutkinalexander@gmail.com>
Project-URL: Homepage, https://github.com/yummydirtx/Licenser
Project-URL: Issues, https://github.com/yummydirtx/Licenser/issues
Classifier: Programming Language :: Python :: 3
Classifier: License :: OSI Approved :: MIT License
Classifier: Operating System :: OS Independent
Requires-Python: >=3.6
License-File: LICENSE
Requires-Dist: argparse
Requires-Dist: InquirerPy
Dynamic: license-file
Dynamic: requires-dist
